pyredpack/__init__.py
pyredpack/functions.py
pyredpack/redis.py
pyredpack-0.2.9.dist-info/LICENSE
pyredpack-0.2.9.dist-info/METADATA
pyredpack-0.2.9.dist-info/WHEEL
pyredpack-0.2.9.dist-info/top_level.txt
pyredpack-0.2.9.dist-info/RECORD
