Metadata-Version: 2.1
Name: pyredpack
Version: 0.2.9
Summary: Serialize any python datatypes and does redis actions using redis-py
Home-page: https://github.com/amirtaherkhani/PyRedPack
Author: amir taherkhani
Author-email: amirtaherkhani@outlook.com
License: MIT
Platform: UNKNOWN
Classifier: Programming Language :: Python :: 3
Classifier: License :: OSI Approved :: MIT License
Classifier: Operating System :: OS Independent
Requires-Python: >=3.8
License-File: LICENSE
Requires-Dist: redis (>=3.4.1)
